README.md
setup.py
webhook/__init__.py
webhook/chandao.py
webhook/gitlab.py
webhook/tower.py
webhook/utils/__init__.py
webhook/utils/time_tools.py
yikai_tools.egg-info/PKG-INFO
yikai_tools.egg-info/SOURCES.txt
yikai_tools.egg-info/dependency_links.txt
yikai_tools.egg-info/requires.txt
yikai_tools.egg-info/top_level.txt