Metadata-Version: 1.1
Name: yikai-tools
Version: 1.0.2
Summary: python modules.
Home-page: https://github.com/happyshi0402/yikai_tools.git
Author: Wang Shifeng
Author-email: wsf121116@163.com
License: MIT
Platform: UNKNOWN
Classifier: Intended Audience :: Developers
Classifier: License :: OSI Approved :: MIT License
Classifier: Natural Language :: English
Classifier: Topic :: Software Development :: Libraries :: Python Modules
Classifier: Operating System :: OS Independent
Classifier: Programming Language :: Python :: 2
Classifier: Programming Language :: Python :: 2.7
